dalila/__init__.py
dalila/dataset_generator.py
dalila/dictionary_learning.py
dalila/parameters_research.py
dalila/penalty.py
dalila/plot.py
dalila/representation_learning.py
dalila/utils.py
dalila-1.0.2.dist-info/DESCRIPTION.rst
dalila-1.0.2.dist-info/METADATA
dalila-1.0.2.dist-info/RECORD
dalila-1.0.2.dist-info/WHEEL
dalila-1.0.2.dist-info/metadata.json
dalila-1.0.2.dist-info/top_level.txt
